my_package/__init__.py
my_package/model.py
titanic_ML_Miguel_Oyarzo-1.0.0.dist-info/METADATA
titanic_ML_Miguel_Oyarzo-1.0.0.dist-info/WHEEL
titanic_ML_Miguel_Oyarzo-1.0.0.dist-info/top_level.txt
titanic_ML_Miguel_Oyarzo-1.0.0.dist-info/RECORD
