Metadata-Version: 2.1
Name: titanic-ML-Miguel-Oyarzo
Version: 1.0.0
Summary: Prediccion en base a variables pclass, sex, age, fare
Home-page: UNKNOWN
Author: Miguel Oyarzo
Author-email: your@email.com
License: UNKNOWN
Platform: UNKNOWN
Classifier: License :: OSI Approved :: MIT License
Classifier: Programming Language :: Python :: 3
Classifier: Programming Language :: Python :: 3.7
Requires-Dist: feature-engine
Requires-Dist: pandas
Requires-Dist: numpy
Requires-Dist: scikit-learn
